NiukeQianduanGangMianshiQiuzhiZhentiJiexi20212022/README.md
NiukeQianduanGangMianshiQiuzhiZhentiJiexi20212022/__init__.py
NiukeQianduanGangMianshiQiuzhiZhentiJiexi20212022/__main__.py
NiukeQianduanGangMianshiQiuzhiZhentiJiexi20212022/file.epub
NiukeQianduanGangMianshiQiuzhiZhentiJiexi20212022/index.html
NiukeQianduanGangMianshiQiuzhiZhentiJiexi20212022/css/__init__.py
NiukeQianduanGangMianshiQiuzhiZhentiJiexi20212022/css/annotations.css
NiukeQianduanGangMianshiQiuzhiZhentiJiexi20212022/css/main.css
NiukeQianduanGangMianshiQiuzhiZhentiJiexi20212022/css/normalize.css
NiukeQianduanGangMianshiQiuzhiZhentiJiexi20212022/css/popup.css
NiukeQianduanGangMianshiQiuzhiZhentiJiexi20212022/font/__init__.py
NiukeQianduanGangMianshiQiuzhiZhentiJiexi20212022/font/fontello.eot
NiukeQianduanGangMianshiQiuzhiZhentiJiexi20212022/font/fontello.svg
NiukeQianduanGangMianshiQiuzhiZhentiJiexi20212022/font/fontello.ttf
NiukeQianduanGangMianshiQiuzhiZhentiJiexi20212022/font/fontello.woff
NiukeQianduanGangMianshiQiuzhiZhentiJiexi20212022/img/__init__.py
NiukeQianduanGangMianshiQiuzhiZhentiJiexi20212022/img/annotator-glyph-sprite.png
NiukeQianduanGangMianshiQiuzhiZhentiJiexi20212022/img/annotator-icon-sprite.png
NiukeQianduanGangMianshiQiuzhiZhentiJiexi20212022/img/apple-touch-icon.png
NiukeQianduanGangMianshiQiuzhiZhentiJiexi20212022/img/cancelfullscreen.png
NiukeQianduanGangMianshiQiuzhiZhentiJiexi20212022/img/close.png
NiukeQianduanGangMianshiQiuzhiZhentiJiexi20212022/img/fullscreen.png
NiukeQianduanGangMianshiQiuzhiZhentiJiexi20212022/img/loader.gif
NiukeQianduanGangMianshiQiuzhiZhentiJiexi20212022/img/menu-icon.png
NiukeQianduanGangMianshiQiuzhiZhentiJiexi20212022/img/save.png
NiukeQianduanGangMianshiQiuzhiZhentiJiexi20212022/img/saved.png
NiukeQianduanGangMianshiQiuzhiZhentiJiexi20212022/img/settings-s.png
NiukeQianduanGangMianshiQiuzhiZhentiJiexi20212022/img/settings.png
NiukeQianduanGangMianshiQiuzhiZhentiJiexi20212022/img/star.png
niuke_qianduan_gang_mianshi_qiuzhi_zhenti_jiexi_2021_2022-2024.3.6.0.dist-info/METADATA
niuke_qianduan_gang_mianshi_qiuzhi_zhenti_jiexi_2021_2022-2024.3.6.0.dist-info/WHEEL
niuke_qianduan_gang_mianshi_qiuzhi_zhenti_jiexi_2021_2022-2024.3.6.0.dist-info/entry_points.txt
niuke_qianduan_gang_mianshi_qiuzhi_zhenti_jiexi_2021_2022-2024.3.6.0.dist-info/top_level.txt
niuke_qianduan_gang_mianshi_qiuzhi_zhenti_jiexi_2021_2022-2024.3.6.0.dist-info/RECORD
